models.py
mosamatic/__init__.py
mosamatic/commands/__init__.py
mosamatic/commands/calculatescores.py
mosamatic/commands/copyfiles.py
mosamatic/commands/createpngsfromsegmentations.py
mosamatic/commands/decompressdicomfiles.py
mosamatic/commands/rescaledicomfiles.py
mosamatic/commands/runpipeline.py
mosamatic/commands/segmentmusclefatl3.py
mosamatic/commands/segmentmusclefatl3tensorflow.py
mosamatic/commands/selectslicefromscan.py
mosamatic/logging.py
mosamatic/main.py
mosamatic/pipelines/__init__.py
mosamatic/pipelines/defaultpipeline.py
mosamatic/pipelines/pipeline.py
mosamatic/singleton.py
mosamatic/tasks/__init__.py
mosamatic/tasks/calculatescorestask/__init__.py
mosamatic/tasks/calculatescorestask/calculatescorestask.py
mosamatic/tasks/copyfilestask/__init__.py
mosamatic/tasks/copyfilestask/copyfilestask.py
mosamatic/tasks/createpngsfromsegmentationstask/__init__.py
mosamatic/tasks/createpngsfromsegmentationstask/createpngsfromsegmentationstask.py
mosamatic/tasks/decompressdicomfilestask/__init__.py
mosamatic/tasks/decompressdicomfilestask/decompressdicomfilestask.py
mosamatic/tasks/rescaledicomfilestask/__init__.py
mosamatic/tasks/rescaledicomfilestask/rescaledicomfilestask.py
mosamatic/tasks/segmentmusclefatl3task/__init__.py
mosamatic/tasks/segmentmusclefatl3task/paramloader.py
mosamatic/tasks/segmentmusclefatl3task/segmentmusclefatl3task.py
mosamatic/tasks/segmentmusclefatl3tensorflowtask/__init__.py
mosamatic/tasks/segmentmusclefatl3tensorflowtask/paramloader.py
mosamatic/tasks/segmentmusclefatl3tensorflowtask/segmentmusclefatl3tensorflowtask.py
mosamatic/tasks/selectslicefromscantask/__init__.py
mosamatic/tasks/selectslicefromscantask/selectslicefromscantask.py
mosamatic/tasks/task.py
mosamatic/utils.py
mosamatic_cli-1.6.7.dist-info/entry_points.txt
mosamatic_cli-1.6.7.dist-info/METADATA
mosamatic_cli-1.6.7.dist-info/WHEEL
mosamatic_cli-1.6.7.dist-info/RECORD
