Metadata-Version: 2.3
Name: mosamatic-cli
Version: 1.6.7
Summary: 
Author: Ralph Brecheisen
Author-email: r.brecheisen@maastrichtuniversity.nl
Requires-Python: >=3.11,<3.12
Classifier: Programming Language :: Python :: 3
Classifier: Programming Language :: Python :: 3.11
Requires-Dist: click
Requires-Dist: nibabel
Requires-Dist: numpy
Requires-Dist: openpyxl
Requires-Dist: pandas
Requires-Dist: pendulum
Requires-Dist: pillow
Requires-Dist: pydicom
Requires-Dist: python-gdcm
Requires-Dist: scipy
Requires-Dist: tensorboard (==2.15.2)
Requires-Dist: tensorboard-data-server (==0.7.2)
Requires-Dist: tensorflow (==2.15.*) ; platform_system == "Linux"
Requires-Dist: tensorflow-intel (==2.15.0) ; platform_system == "Windows"
Requires-Dist: tensorflow-io-gcs-filesystem (==0.31.0)
Requires-Dist: tensorflow-macos (==2.15.0) ; platform_system == "Darwin" and platform_machine == "arm64"
Requires-Dist: torch
Requires-Dist: torchvision
Requires-Dist: totalsegmentator
